testpypiMP/__init__.py
testpypiMP/m_mod_mp.py
testpypiMP-0.0.1.dist-info/LICENSE.txt
testpypiMP-0.0.1.dist-info/METADATA
testpypiMP-0.0.1.dist-info/WHEEL
testpypiMP-0.0.1.dist-info/top_level.txt
testpypiMP-0.0.1.dist-info/RECORD
