Metadata-Version: 2.1
Name: testpypiMP
Version: 0.0.1
Summary: My test package
Author-email: MP <puchal71@gmail.com>
License: MIT License
Keywords: testpypiMP,name,surname,fun funkction
Classifier: Framework :: Ansible
Classifier: Framework :: Zope2
Requires-Python: >=3.0
License-File: LICENSE.txt
Requires-Dist: numpy
